{
  "frontier": [
    {
      "season": "10",
      "pickRate": 100
    },
    {
      "season": "11",
      "pickRate": 100
    },
    {
      "season": "12",
      "pickRate": 99.7
    },
    {
      "season": "2",
      "pickRate": 97
    },
    {
      "season": "4",
      "pickRate": 98
    },
    {
      "season": "5",
      "pickRate": 98
    },
    {
      "season": "6",
      "pickRate": 94
    },
    {
      "season": "7",
      "pickRate": 98
    },
    {
      "season": "8",
      "pickRate": 100
    },
    {
      "season": "9",
      "pickRate": 99
    }
  ],
  "clash": [
    {
      "season": "17",
      "pickRate": 80
    },
    {
      "season": "20",
      "pickRate": 17
    },
    {
      "season": "31",
      "pickRate": 93
    },
    {
      "season": "32",
      "pickRate": 93
    },
    {
      "season": "33",
      "pickRate": 98
    },
    {
      "season": "34",
      "pickRate": 42
    },
    {
      "season": "35",
      "pickRate": 65.7
    },
    {
      "season": "36",
      "pickRate": 95.3
    },
    {
      "season": "37",
      "pickRate": 58.7
    },
    {
      "season": "38",
      "pickRate": 83
    },
    {
      "season": "39",
      "pickRate": 98.7
    }
  ]
}